{"type": "FeatureCollection", "id": "https://en.wikipedia.org/wiki/Kostyonki%E2%80%93Borshchyovo", "name": "Kostyonki%E2%80%93Borshchyovo", "features": [{"type": "Feature", "id": "http://w3id.org/geo-lod/ci/cisite_59", "name": "", "dateprops": [], "properties": {"http://fuzzy-sl.squirrel.link/ontology/dubiousMatch": ["https://en.wikipedia.org/wiki/Kostyonki%E2%80%93Borshchyovo"], "http://purl.org/dc/terms/creator": ["https://orcid.org/0000-0002-3246-3531", "https://orcid.org/0000-0003-1100-6494"], "http://purl.org/dc/terms/license": ["https://creativecommons.org/licenses/by/4.0/"], "http://purl.org/dc/terms/rightsHolder": ["https://orcid.org/0000-0002-3246-3531", "https://orcid.org/0000-0003-1100-6494"], "http://rdfs.org/ns/void#inDataset": ["http://w3id.org/geo-lod/geo-lod"], "http://w3id.org/geo-lod/hasCertaintyDescription": ["findspot mentioned in a scientific paper"], "http://w3id.org/geo-lod/hasCertaintyLevel": ["http://fuzzy-sl.squirrel.link/ontology/representative"], "http://w3id.org/geo-lod/hasLiteratureReference": ["Fedele et al., 2008", "Giaccio et al., 2008"], "http://w3id.org/geo-lod/hasSpatialType": ["http://fuzzy-sl.squirrel.link/ontology/ArchaeologicalSite"], "http://www.opengis.net/ont/geosparql#hasGeometry": ["http://w3id.org/geo-lod/ci/cisite_59_geom"], "http://www.w3.org/1999/02/22-rdf-syntax-ns#type": ["http://fuzzy-sl.squirrel.link/ontology/Site", "http://w3id.org/geo-lod/CIArchaeologicalSite", "http://w3id.org/geo-lod/CIFindspot", "http://www.cidoc-crm.org/crmarchaeo/A2_Stratigraphic_Volume_Unit", "http://www.w3.org/ns/prov#Entity", "https://pleiades.stoa.org/places/vocab#Place"], "http://www.w3.org/2000/01/rdf-schema#comment": ["CI findspot related from literature"], "http://www.w3.org/2000/01/rdf-schema#label": ["Kostenki-Borshchevo (Russia)"], "http://www.w3.org/2004/02/skos/core#prefLabel": ["Kostenki-Borshchevo (Russia)"], "http://www.w3.org/2004/02/skos/core#scopeNote": ["CI findspot related from literature"], "http://www.w3.org/ns/prov#wasAttributedTo": ["http://orcid.org/0009-0008-2877-3204", "https://github.com/Research-Squirrel-Engineers/campanian-ignimbrite-geo/blob/main/py/CI.py"], "http://www.w3.org/ns/prov#wasDerivedFrom": ["https://github.com/Research-Squirrel-Engineers/campanian-ignimbrite-geo"], "http://www.w3.org/ns/prov#wasGeneratedBy": ["http://w3id.org/geo-lod/ci/cisite_59_activity", "http://w3id.org/geo-lod/ci/cisite_59_pyscript"]}, "geometry": {"type": "Point", "coordinates": [39.0517, 51.3858], "crs": "4326"}, "crs": "EPSG:4326"}], "numberMatched": 1, "numberReturned": 1, "bbox": [39.0517, 51.3858, 39.0517, 51.3858], "crs": "http://www.opengis.net/def/crs/EPSG/0/EPSG:4326"}